accelerator_utils/__init__.py
accelerator_utils/file_interfaces.py
accelerator_physics-0.0.1.dist-info/LICENSE.txt
accelerator_physics-0.0.1.dist-info/METADATA
accelerator_physics-0.0.1.dist-info/WHEEL
accelerator_physics-0.0.1.dist-info/top_level.txt
accelerator_physics-0.0.1.dist-info/RECORD
