Metadata-Version: 2.1
Name: accelerator_physics
Version: 0.0.1
Summary: Sharing useful python functions for accelerator physics with the public
Author-email: "Christopher M. Pierce" <contact@chris-pierce.com>
License: BSD 3-Clause License
Classifier: Programming Language :: Python :: 3
Classifier: Operating System :: OS Independent
Requires-Python: >=3.7
License-File: LICENSE.txt
Requires-Dist: pandas
Requires-Dist: numpy
Requires-Dist: pillow
